JianZhiOfferDierBanQuanjieDoocsKaiyuanShequFix1/README.md
JianZhiOfferDierBanQuanjieDoocsKaiyuanShequFix1/__init__.py
JianZhiOfferDierBanQuanjieDoocsKaiyuanShequFix1/__main__.py
JianZhiOfferDierBanQuanjieDoocsKaiyuanShequFix1/file.epub
JianZhiOfferDierBanQuanjieDoocsKaiyuanShequFix1/index.html
JianZhiOfferDierBanQuanjieDoocsKaiyuanShequFix1/css/__init__.py
JianZhiOfferDierBanQuanjieDoocsKaiyuanShequFix1/css/annotations.css
JianZhiOfferDierBanQuanjieDoocsKaiyuanShequFix1/css/main.css
JianZhiOfferDierBanQuanjieDoocsKaiyuanShequFix1/css/normalize.css
JianZhiOfferDierBanQuanjieDoocsKaiyuanShequFix1/css/popup.css
JianZhiOfferDierBanQuanjieDoocsKaiyuanShequFix1/font/__init__.py
JianZhiOfferDierBanQuanjieDoocsKaiyuanShequFix1/font/fontello.eot
JianZhiOfferDierBanQuanjieDoocsKaiyuanShequFix1/font/fontello.svg
JianZhiOfferDierBanQuanjieDoocsKaiyuanShequFix1/font/fontello.ttf
JianZhiOfferDierBanQuanjieDoocsKaiyuanShequFix1/font/fontello.woff
JianZhiOfferDierBanQuanjieDoocsKaiyuanShequFix1/img/__init__.py
JianZhiOfferDierBanQuanjieDoocsKaiyuanShequFix1/img/annotator-glyph-sprite.png
JianZhiOfferDierBanQuanjieDoocsKaiyuanShequFix1/img/annotator-icon-sprite.png
JianZhiOfferDierBanQuanjieDoocsKaiyuanShequFix1/img/apple-touch-icon.png
JianZhiOfferDierBanQuanjieDoocsKaiyuanShequFix1/img/cancelfullscreen.png
JianZhiOfferDierBanQuanjieDoocsKaiyuanShequFix1/img/close.png
JianZhiOfferDierBanQuanjieDoocsKaiyuanShequFix1/img/fullscreen.png
JianZhiOfferDierBanQuanjieDoocsKaiyuanShequFix1/img/loader.gif
JianZhiOfferDierBanQuanjieDoocsKaiyuanShequFix1/img/menu-icon.png
JianZhiOfferDierBanQuanjieDoocsKaiyuanShequFix1/img/save.png
JianZhiOfferDierBanQuanjieDoocsKaiyuanShequFix1/img/saved.png
JianZhiOfferDierBanQuanjieDoocsKaiyuanShequFix1/img/settings-s.png
JianZhiOfferDierBanQuanjieDoocsKaiyuanShequFix1/img/settings.png
JianZhiOfferDierBanQuanjieDoocsKaiyuanShequFix1/img/star.png
JianZhiOfferDierBanQuanjieDoocsKaiyuanShequFix1/js/__init__.py
jian_zhi_offer_dier_ban_quanjie_doocs_kaiyuan_shequ_fix1-2025.3.25.0.dist-info/METADATA
jian_zhi_offer_dier_ban_quanjie_doocs_kaiyuan_shequ_fix1-2025.3.25.0.dist-info/WHEEL
jian_zhi_offer_dier_ban_quanjie_doocs_kaiyuan_shequ_fix1-2025.3.25.0.dist-info/entry_points.txt
jian_zhi_offer_dier_ban_quanjie_doocs_kaiyuan_shequ_fix1-2025.3.25.0.dist-info/top_level.txt
jian_zhi_offer_dier_ban_quanjie_doocs_kaiyuan_shequ_fix1-2025.3.25.0.dist-info/RECORD
